[{"submitTimestamp":"9:22 AM","customerName":"Ruth Russell","customerEmail":"jhill0@spotify.com","description":"Nam dui.","isOpen":false,"closedTimestamp":"8:12 AM","employeeName":"Joshua Hill"},
{"submitTimestamp":"3:13 AM","customerName":"Anna Fields","customerEmail":"rmorgan1@salon.com","description":"Sed ante.","isOpen":false,"closedTimestamp":"8:35 AM","employeeName":"Ruby Morgan"},
{"submitTimestamp":"3:38 PM","customerName":"Patricia Daniels","customerEmail":"dkennedy2@1688.com","description":"Pellentesque eget nunc.","isOpen":false,"closedTimestamp":"1:26 PM","employeeName":"Donald Kennedy"},
{"submitTimestamp":"12:16 AM","customerName":"Lois Mills","customerEmail":"lwillis3@timesonline.co.uk","description":"Suspendisse potenti.","isOpen":false,"closedTimestamp":"12:14 AM","employeeName":"Lori Willis"},
{"submitTimestamp":"6:51 AM","customerName":"Steve Mccoy","customerEmail":"rjones4@delicious.com","description":"Nunc nisl.","isOpen":false,"closedTimestamp":"3:29 AM","employeeName":"Ryan Jones"},
{"submitTimestamp":"11:52 AM","customerName":"Jennifer Ellis","customerEmail":"gclark5@mozilla.com","description":"Nulla tellus.","isOpen":false,"closedTimestamp":"12:29 PM","employeeName":"Gloria Clark"},
{"submitTimestamp":"1:10 AM","customerName":"Pamela Ward","customerEmail":"agray6@harvard.edu","description":"Phasellus in felis.","isOpen":false,"closedTimestamp":"7:54 PM","employeeName":"Andrea Gray"},
{"submitTimestamp":"10:11 PM","customerName":"Tina Cooper","customerEmail":"creed7@loc.gov","description":"Maecenas leo odio, condimentum id, luctus nec, molestie sed, justo.","isOpen":true,"closedTimestamp":"","employeeName":"Carl Reed"},
{"submitTimestamp":"10:41 PM","customerName":"Rachel Owens","customerEmail":"smason8@cnn.com","description":"Duis consequat dui nec nisi volutpat eleifend.","isOpen":true,"closedTimestamp":"","employeeName":"Sharon Mason"},
{"submitTimestamp":"3:20 AM","customerName":"Sharon Garrett","customerEmail":"aduncan9@arstechnica.com","description":"Etiam faucibus cursus urna.","isOpen":false,"closedTimestamp":"7:20 AM","employeeName":"Antonio Duncan"},
{"submitTimestamp":"5:29 PM","customerName":"Pamela Foster","customerEmail":"mlyncha@xing.com","description":"Suspendisse potenti.","isOpen":true,"closedTimestamp":"","employeeName":"Michael Lynch"},
{"submitTimestamp":"12:22 AM","customerName":"Cheryl Fox","customerEmail":"wlynchb@fotki.com","description":"Maecenas rhoncus aliquam lacus.","isOpen":true,"closedTimestamp":"","employeeName":"Wayne Lynch"},
{"submitTimestamp":"9:16 PM","customerName":"Joseph Andrews","customerEmail":"ggonzalezc@exblog.jp","description":"Aliquam non mauris.","isOpen":false,"closedTimestamp":"1:41 PM","employeeName":"George Gonzalez"},
{"submitTimestamp":"10:14 AM","customerName":"Aaron Black","customerEmail":"lgibsond@washington.edu","description":"Maecenas pulvinar lobortis est.","isOpen":true,"closedTimestamp":"","employeeName":"Lois Gibson"},
{"submitTimestamp":"9:54 PM","customerName":"Lois Kim","customerEmail":"breede@usa.gov","description":"Nulla ut erat id mauris vulputate elementum.","isOpen":true,"closedTimestamp":"","employeeName":"Brian Reed"},
{"submitTimestamp":"12:09 AM","customerName":"Harry Brown","customerEmail":"shamiltonf@yolasite.com","description":"Praesent blandit lacinia erat.","isOpen":false,"closedTimestamp":"12:38 AM","employeeName":"Sara Hamilton"},
{"submitTimestamp":"7:32 PM","customerName":"Jane Rogers","customerEmail":"emcdonaldg@scribd.com","description":"Mauris ullamcorper purus sit amet nulla.","isOpen":false,"closedTimestamp":"9:14 AM","employeeName":"Elizabeth Mcdonald"},
{"submitTimestamp":"11:19 AM","customerName":"Norma Schmidt","customerEmail":"ereynoldsh@tinypic.com","description":"Mauris enim leo, rhoncus sed, vestibulum sit amet, cursus id, turpis.","isOpen":false,"closedTimestamp":"7:19 PM","employeeName":"Evelyn Reynolds"},
{"submitTimestamp":"7:51 AM","customerName":"Mark Medina","customerEmail":"sdunni@msn.com","description":"Sed ante.","isOpen":false,"closedTimestamp":"4:31 AM","employeeName":"Sarah Dunn"},
{"submitTimestamp":"2:10 PM","customerName":"Debra Ortiz","customerEmail":"djacobsj@123-reg.co.uk","description":"Aenean fermentum.","isOpen":true,"closedTimestamp":"","employeeName":"Debra Jacobs"},
{"submitTimestamp":"1:16 AM","customerName":"Ernest Russell","customerEmail":"pcastillok@bing.com","description":"Vestibulum quam sapien, varius ut, blandit non, interdum in, ante.","isOpen":true,"closedTimestamp":"","employeeName":"Peter Castillo"},
{"submitTimestamp":"1:48 PM","customerName":"Debra Sanchez","customerEmail":"igriffinl@clickbank.net","description":"Vestibulum ante ipsum primis in faucibus orci luctus et ultrices posuere cubilia Curae; Mauris viverra diam vitae quam.","isOpen":true,"closedTimestamp":"","employeeName":"Irene Griffin"},
{"submitTimestamp":"12:21 AM","customerName":"Evelyn Harris","customerEmail":"jdavism@barnesandnoble.com","description":"Etiam faucibus cursus urna.","isOpen":false,"closedTimestamp":"1:20 AM","employeeName":"Jeffrey Davis"},
{"submitTimestamp":"3:21 PM","customerName":"Brian Gonzales","customerEmail":"kmorgann@weebly.com","description":"Phasellus sit amet erat.","isOpen":true,"closedTimestamp":"","employeeName":"Kenneth Morgan"},
{"submitTimestamp":"11:43 AM","customerName":"Eugene Berry","customerEmail":"cmorrisono@earthlink.net","description":"Morbi odio odio, elementum eu, interdum eu, tincidunt in, leo.","isOpen":true,"closedTimestamp":"","employeeName":"Catherine Morrison"},
{"submitTimestamp":"12:53 AM","customerName":"Frank Fisher","customerEmail":"probertsonp@networksolutions.com","description":"Aliquam sit amet diam in magna bibendum imperdiet.","isOpen":false,"closedTimestamp":"9:41 PM","employeeName":"Paula Robertson"},
{"submitTimestamp":"1:52 AM","customerName":"David Thompson","customerEmail":"jandersonq@google.com.br","description":"Proin leo odio, porttitor id, consequat in, consequat ut, nulla.","isOpen":true,"closedTimestamp":"","employeeName":"Judith Anderson"},
{"submitTimestamp":"1:07 PM","customerName":"Brian Wood","customerEmail":"vryanr@amazonaws.com","description":"Nullam orci pede, venenatis non, sodales sed, tincidunt eu, felis.","isOpen":false,"closedTimestamp":"8:09 PM","employeeName":"Victor Ryan"},
{"submitTimestamp":"8:31 AM","customerName":"John Fox","customerEmail":"rdeans@bravesites.com","description":"Pellentesque at nulla.","isOpen":false,"closedTimestamp":"5:05 PM","employeeName":"Robert Dean"},
{"submitTimestamp":"7:05 AM","customerName":"Mary Taylor","customerEmail":"jmartinezt@epa.gov","description":"Pellentesque ultrices mattis odio.","isOpen":false,"closedTimestamp":"2:58 PM","employeeName":"Janice Martinez"},
{"submitTimestamp":"6:14 PM","customerName":"Ruth Gray","customerEmail":"jcooku@instagram.com","description":"Nulla ac enim.","isOpen":true,"closedTimestamp":"","employeeName":"Jean Cook"},
{"submitTimestamp":"4:18 AM","customerName":"Janet Rice","customerEmail":"jmendozav@csmonitor.com","description":"Sed ante.","isOpen":true,"closedTimestamp":"","employeeName":"Jonathan Mendoza"},
{"submitTimestamp":"7:39 PM","customerName":"Michelle Baker","customerEmail":"storresw@pen.io","description":"Ut at dolor quis odio consequat varius.","isOpen":true,"closedTimestamp":"","employeeName":"Sara Torres"},
{"submitTimestamp":"6:12 PM","customerName":"Diane Howard","customerEmail":"dpalmerx@feedburner.com","description":"Donec dapibus.","isOpen":false,"closedTimestamp":"2:00 PM","employeeName":"Donna Palmer"},
{"submitTimestamp":"11:30 AM","customerName":"Philip Baker","customerEmail":"gwatkinsy@bizjournals.com","description":"Duis bibendum, felis sed interdum venenatis, turpis enim blandit mi, in porttitor pede justo eu massa.","isOpen":false,"closedTimestamp":"1:59 PM","employeeName":"Gregory Watkins"},
{"submitTimestamp":"2:05 AM","customerName":"Sharon Carpenter","customerEmail":"cbanksz@washingtonpost.com","description":"Phasellus in felis.","isOpen":false,"closedTimestamp":"7:00 PM","employeeName":"Chris Banks"},
{"submitTimestamp":"7:27 PM","customerName":"John Ray","customerEmail":"sgutierrez10@pinterest.com","description":"Curabitur in libero ut massa volutpat convallis.","isOpen":true,"closedTimestamp":"","employeeName":"Steve Gutierrez"},
{"submitTimestamp":"7:27 AM","customerName":"Amy Henry","customerEmail":"pwilson11@t.co","description":"Integer a nibh.","isOpen":false,"closedTimestamp":"12:06 AM","employeeName":"Peter Wilson"},
{"submitTimestamp":"4:12 AM","customerName":"Ralph Reynolds","customerEmail":"fcook12@senate.gov","description":"In congue.","isOpen":true,"closedTimestamp":"","employeeName":"Frank Cook"},
{"submitTimestamp":"11:10 PM","customerName":"Rebecca Bryant","customerEmail":"acox13@wiley.com","description":"Sed vel enim sit amet nunc viverra dapibus.","isOpen":true,"closedTimestamp":"","employeeName":"Antonio Cox"},
{"submitTimestamp":"10:56 PM","customerName":"Brandon Harrison","customerEmail":"itaylor14@typepad.com","description":"Sed vel enim sit amet nunc viverra dapibus.","isOpen":true,"closedTimestamp":"","employeeName":"Irene Taylor"},
{"submitTimestamp":"7:22 AM","customerName":"Evelyn Warren","customerEmail":"bdaniels15@indiatimes.com","description":"In quis justo.","isOpen":false,"closedTimestamp":"10:16 AM","employeeName":"Brandon Daniels"},
{"submitTimestamp":"4:45 AM","customerName":"Bobby Pierce","customerEmail":"ggardner16@ovh.net","description":"Phasellus in felis.","isOpen":true,"closedTimestamp":"","employeeName":"Gerald Gardner"},
{"submitTimestamp":"3:57 AM","customerName":"Marilyn Palmer","customerEmail":"slong17@ebay.com","description":"Integer pede justo, lacinia eget, tincidunt eget, tempus vel, pede.","isOpen":false,"closedTimestamp":"8:40 PM","employeeName":"Stephanie Long"},
{"submitTimestamp":"9:48 PM","customerName":"Heather Griffin","customerEmail":"ndixon18@infoseek.co.jp","description":"Donec ut mauris eget massa tempor convallis.","isOpen":true,"closedTimestamp":"","employeeName":"Norma Dixon"},
{"submitTimestamp":"9:46 AM","customerName":"Carol Weaver","customerEmail":"srodriguez19@europa.eu","description":"Fusce consequat.","isOpen":false,"closedTimestamp":"9:58 PM","employeeName":"Sean Rodriguez"},
{"submitTimestamp":"9:00 AM","customerName":"Joshua Williamson","customerEmail":"jknight1a@amazonaws.com","description":"Maecenas pulvinar lobortis est.","isOpen":true,"closedTimestamp":"","employeeName":"Jessica Knight"},
{"submitTimestamp":"10:36 PM","customerName":"Ryan Wright","customerEmail":"kwilliamson1b@wp.com","description":"Cras mi pede, malesuada in, imperdiet et, commodo vulputate, justo.","isOpen":true,"closedTimestamp":"","employeeName":"Katherine Williamson"},
{"submitTimestamp":"4:10 PM","customerName":"Evelyn Boyd","customerEmail":"cross1c@bbb.org","description":"Donec posuere metus vitae ipsum.","isOpen":false,"closedTimestamp":"6:47 PM","employeeName":"Cynthia Ross"},
{"submitTimestamp":"3:23 AM","customerName":"Nicholas Richardson","customerEmail":"jlee1d@netvibes.com","description":"Integer tincidunt ante vel ipsum.","isOpen":true,"closedTimestamp":"","employeeName":"Jean Lee"}]
